scrapy_sink/__init__.py
scrapy_sink/pipelines.py
scrapy_sink/simple.py
scrapy_sink-0.1.2.dist-info/METADATA
scrapy_sink-0.1.2.dist-info/WHEEL
scrapy_sink-0.1.2.dist-info/top_level.txt
scrapy_sink-0.1.2.dist-info/RECORD
